booster/__init__.py
booster-0.0.1.dist-info/DESCRIPTION.rst
booster-0.0.1.dist-info/METADATA
booster-0.0.1.dist-info/RECORD
booster-0.0.1.dist-info/WHEEL
booster-0.0.1.dist-info/metadata.json
booster-0.0.1.dist-info/top_level.txt
