Metadata-Version: 2.0
Name: booster
Version: 0.0.1
Summary: Boost your project
Home-page: UNKNOWN
Author: Yusuke Sugomori
Author-email: me@yusugomori.com
License: UNKNOWN
Platform: UNKNOWN
Classifier: Development Status :: 1 - Planning
